setup.py
lcdproc/__init__.py
lcdproc/screen.py
lcdproc/server.py
lcdproc/widgets.py
lcdproc.egg-info/PKG-INFO
lcdproc.egg-info/SOURCES.txt
lcdproc.egg-info/dependency_links.txt
lcdproc.egg-info/top_level.txt