Metadata-Version: 1.0
Name: lcdproc
Version: 0.03
Summary: Python OOP Wrapper Library for LCDproc Telnet API
Home-page: http://github.com/jingleman/lcdproc
Author: JingleManSweep
Author-email: jinglemansweep@gmail.com
License: UNKNOWN
Platform: UNKNOWN
